strands_vllm/__init__.py
strands_vllm/recorder.py
strands_vllm/token.py
strands_vllm/tool_validation.py
strands_vllm/vllm.py
strands_vllm-0.0.4.dist-info/METADATA
strands_vllm-0.0.4.dist-info/WHEEL
strands_vllm-0.0.4.dist-info/licenses/LICENSE
strands_vllm-0.0.4.dist-info/RECORD
