Metadata-Version: 2.4
Name: strands-vllm
Version: 0.0.4
Summary: Community vLLM provider utilities for Strands Agents (OpenAI-compatible).
Project-URL: Homepage, https://github.com/agents-community/strands-vllm
Project-URL: Repository, https://github.com/agents-community/strands-vllm
Project-URL: Issues, https://github.com/agents-community/strands-vllm/issues
Author: Strands Community
License: Apache-2.0
License-File: LICENSE
Keywords: agents,llm,openai,strands,vllm
Classifier: Development Status :: 3 - Alpha
Classifier: Intended Audience :: Developers
Classifier: License :: OSI Approved :: Apache Software License
Classifier: Programming Language :: Python :: 3
Classifier: Programming Language :: Python :: 3.10
Classifier: Programming Language :: Python :: 3.11
Classifier: Programming Language :: Python :: 3.12
Classifier: Programming Language :: Python :: 3.13
Classifier: Topic :: Scientific/Engineering :: Artificial Intelligence
Requires-Python: >=3.10
Requires-Dist: openai<2.0.0,>=1.68.0
Requires-Dist: strands-agents
Provides-Extra: dev
Requires-Dist: pytest-asyncio<1.4.0,>=1.0.0; extra == 'dev'
Requires-Dist: pytest<9.0.0,>=8.0.0; extra == 'dev'
Requires-Dist: ruff<0.15.0,>=0.13.0; extra == 'dev'
Requires-Dist: strands-agents-tools; extra == 'dev'
Provides-Extra: drift
Requires-Dist: transformers; extra == 'drift'
